inmanta_ext/ui/__init__.py
inmanta_ext/ui/extension.py
inmanta_ui/__init__.py
inmanta_ui/config.py
inmanta_ui/const.py
inmanta_ui/ui.py
inmanta_ui-6.0.1.dist-info/licenses/LICENSE
inmanta_ui-6.0.1.dist-info/METADATA
inmanta_ui-6.0.1.dist-info/WHEEL
inmanta_ui-6.0.1.dist-info/top_level.txt
inmanta_ui-6.0.1.dist-info/RECORD
