Metadata-Version: 2.4
Name: inmanta-ui
Version: 6.0.1
Summary: Slice serving the inmanta UI
Home-page: https://github.com/inmanta/inmanta-ui
Author: Inmanta
Author-email: code@inmanta.com
License: ASL 2.0
Project-URL: Bug Tracker, https://github.com/inmanta/inmanta-ui/issues
Requires-Python: >=3.11
License-File: LICENSE
Requires-Dist: inmanta-core>=11.1.0
Requires-Dist: tornado~=6.0
Provides-Extra: dev
Requires-Dist: bumpversion; extra == "dev"
Requires-Dist: inmanta-dev-dependencies[async,extension,pytest]; extra == "dev"
Dynamic: author
Dynamic: author-email
Dynamic: home-page
Dynamic: license
Dynamic: license-file
Dynamic: project-url
Dynamic: provides-extra
Dynamic: requires-dist
Dynamic: requires-python
Dynamic: summary
